sqlalchemy_auth/LICENSE
sqlalchemy_auth/__init__.py
sqlalchemy_auth/auth_base.py
sqlalchemy_auth/auth_query.py
sqlalchemy_auth/auth_query_test.py
sqlalchemy_auth/auth_session.py
sqlalchemy_auth/auth_session_test.py
sqlalchemy_auth/block_base.py
sqlalchemy_auth/block_base_test.py
sqlalchemy_auth/utils.py
sqlalchemy_auth-1.2.8.dist-info/METADATA
sqlalchemy_auth-1.2.8.dist-info/RECORD
sqlalchemy_auth-1.2.8.dist-info/WHEEL
sqlalchemy_auth-1.2.8.dist-info/entry_points.txt
sqlalchemy_auth-1.2.8.dist-info/top_level.txt
