Metadata-Version: 2.1
Name: sqlalchemy-auth
Version: 1.2.8
Summary: Provides authorization mechanisms for SQLAlchemy
Home-page: https://github.com/dhiltonp/sqlalchemy_auth
Author: David P Hilton
Author-email: david.hilton.p@gmail.com
License: mit
Platform: any
Classifier: Development Status :: 5 - Production/Stable
Classifier: Intended Audience :: Developers
Classifier: License :: OSI Approved :: MIT License
Classifier: Programming Language :: Python
Classifier: Programming Language :: Python :: 3
Classifier: Programming Language :: Python :: 3.4
Classifier: Programming Language :: Python :: 3.5
Classifier: Programming Language :: Python :: 3.6
Classifier: Programming Language :: Python :: 3.7
Classifier: Programming Language :: Python :: Implementation :: CPython
Classifier: Programming Language :: Python :: Implementation :: PyPy
Classifier: Topic :: Database
Classifier: Operating System :: OS Independent
Requires-Dist: sqlalchemy
